ambition_dashboard/__init__.py
ambition_dashboard/apps.py
ambition_dashboard/navbars.py
ambition_dashboard/patterns.py
ambition_dashboard/urls.py
ambition_dashboard/wsgi.py
ambition_dashboard/model_wrappers/__init__.py
ambition_dashboard/model_wrappers/subject_screening_model_wrapper.py
ambition_dashboard/templates/ambition_dashboard/bootstrap3/buttons/add_consent_button.html
ambition_dashboard/templates/ambition_dashboard/bootstrap3/buttons/dashboard_button.html
ambition_dashboard/templates/ambition_dashboard/bootstrap3/buttons/eligibility_button.html
ambition_dashboard/templates/ambition_dashboard/bootstrap3/buttons/screening_button.html
ambition_dashboard/templates/ambition_dashboard/bootstrap3/screening/listboard.html
ambition_dashboard/templates/ambition_dashboard/bootstrap3/subject/dashboard.html
ambition_dashboard/templates/ambition_dashboard/bootstrap3/subject/listboard.html
ambition_dashboard/templates/ambition_dashboard/bootstrap3/subject/dashboard/top_bar.html
ambition_dashboard/templatetags/__init__.py
ambition_dashboard/templatetags/ambition_dashboard_extras.py
ambition_dashboard/tests/__init__.py
ambition_dashboard/tests/admin.py
ambition_dashboard/tests/urls.py
ambition_dashboard/tests/tests/__init__.py
ambition_dashboard/tests/tests/test_model_wrappers.py
ambition_dashboard/views/__init__.py
ambition_dashboard/views/ae/__init__.py
ambition_dashboard/views/ae/ae_listboard_view.py
ambition_dashboard/views/ae/death_report_listboard_view.py
ambition_dashboard/views/screening/__init__.py
ambition_dashboard/views/screening/filters.py
ambition_dashboard/views/screening/listboard_view.py
ambition_dashboard/views/subject/__init__.py
ambition_dashboard/views/subject/dashboard/__init__.py
ambition_dashboard/views/subject/dashboard/dashboard_view.py
ambition_dashboard/views/subject/listboard/__init__.py
ambition_dashboard/views/subject/listboard/listboard_view.py
ambition_dashboard/views/tmg/__init__.py
ambition_dashboard/views/tmg/tmg_death_listboard_view.py
ambition_dashboard-0.1.47.dist-info/AUTHORS
ambition_dashboard-0.1.47.dist-info/LICENSE
ambition_dashboard-0.1.47.dist-info/METADATA
ambition_dashboard-0.1.47.dist-info/WHEEL
ambition_dashboard-0.1.47.dist-info/top_level.txt
ambition_dashboard-0.1.47.dist-info/RECORD
