Metadata-Version: 2.1
Name: ambition-dashboard
Version: 0.1.47
Summary: Dashboard for ambition/edc
Home-page: https://github.com/ambition-trial/ambition-dashboard
Author: Erik van Widenfelt
Author-email: ew2789@gmail.com
License: GPL license, see LICENSE
Keywords: django ambition dashboard
Platform: UNKNOWN
Classifier: Environment :: Web Environment
Classifier: Framework :: Django
Classifier: Intended Audience :: Developers
Classifier: Intended Audience :: Science/Research
Classifier: License :: OSI Approved :: GNU General Public License v3 (GPLv3)
Classifier: Operating System :: OS Independent
Classifier: Programming Language :: Python :: 3.7
Classifier: Topic :: Internet :: WWW/HTTP
Classifier: Topic :: Internet :: WWW/HTTP :: Dynamic Content
Requires-Python: >=3.7
Requires-Dist: ambition-ae
Requires-Dist: ambition-lists
Requires-Dist: ambition-permissions
Requires-Dist: ambition-prn
Requires-Dist: ambition-rando
Requires-Dist: ambition-reports
Requires-Dist: ambition-subject
Requires-Dist: edc-appointment
Requires-Dist: edc-consent
Requires-Dist: edc-constants
Requires-Dist: edc-dashboard
Requires-Dist: edc-lab-dashboard
Requires-Dist: edc-model-wrapper
Requires-Dist: edc-navbar
Requires-Dist: edc-subject-dashboard
Requires-Dist: edc-review-dashboard
